{
    "success": {
        "code": 200,
        "data": {
            "object": "ride-details",
            "id": "769cf5c5",
            "rideStatus": 0,
            "createdAt": "2025-12-17 13:38:37",
            "acceptedAt": null,
            "rideCost": 42.0,
            "serviceName": "Jump start",
            "paymentStatus": 2,
            "rideRating": 0,
            "customerDetails": {
                "id": "769cfb70",
                "name": "jhon wick",
                "email": "waleed+131@progstream.com",
                "phone": "+1(310)2836523",
                "profileImage": "https://progstream.s3.amazonaws.com/rdaid/dev/file_1765374921193.png",
                "ratingCount": 0,
                "ratingAvg": 0,
                "callMeAllowed": true
            },
            "serviceDetails": {
                "object": "service",
                "id": "769cfd70",
                "title": "Jump start",
                "description": "qeqwe",
                "durationInMin": 30,
                "expirationDate": null,
                "serviceFor": 0,
                "driverCount": 25,
                "addedBy": 498,
                "updatedBy": null,
                "status": "active",
                "servicePrice": {
                    "object": "servicePrice",
                    "id": "769cfd70",
                    "serviceId": "769cfd70",
                    "paymentType": 1,
                    "serviceCharges": 40.0,
                    "distance": null,
                    "chargesPerUnit": null,
                    "chargesPerUnitAfterSlab": null,
                    "adjustablePrice": true,
                    "allowNightShift": true,
                    "unit": "miles",
                    "createdAt": "2025-11-10 08:43:01",
                    "updatedAt": "2025-11-10 08:43:01"
                },
                "serviceIconUrl": null,
                "driverOnline": 0,
                "cancellationFeePercent": 10.0,
                "createdAt": "2025-11-10 08:43:01",
                "updatedAt": "2025-11-10 08:43:01"
            },
            "vehicleDetails": {
                "object": "vehicle",
                "id": "769cfac1",
                "userId": "769cfb70",
                "make": "Dodge",
                "model": "Neon",
                "year": "2025",
                "color": "Red",
                "fuelType": "Gasoline",
                "tireSize": "272/72/R72",
                "identificationNumber": null,
                "registrationNumber": null,
                "stateOfRegistration": null,
                "licensePlateNo": "377373737",
                "expirationDate": null,
                "towTruck": false,
                "default": null,
                "status": "pending",
                "createdAt": "2025-12-11 06:38:39",
                "updatedAt": "2025-12-11 06:39:43",
                "attachmentUrl": "https://progstream.s3.amazonaws.com/rdaid/dev/file_1765435119661.png"
            },
            "pickUpLocation": {
                "object": "location",
                "id": "769ceec5",
                "user_id": "769cfb70",
                "latitude": 24.92359815836041,
                "longitude": 67.0917895808816,
                "country": null,
                "state": null,
                "city": null,
                "streetAddress": "W3FR+CP Gulshan-e-Iqbal, Karachi, Pakistan",
                "homeAddress": null,
                "postalCode": null,
                "apartment": null,
                "modelId": "769cf5c5",
                "modelType": "Ride",
                "status": "active",
                "createdAt": "2025-12-17 13:38:37",
                "updatedAt": "2025-12-17 13:38:37"
            },
            "userAnswers": [],
            "driverDetails": null,
            "estimatedRideCost": 0,
            "driverArrivalTime": 0,
            "driverDistance": "0 miles",
            "rideAttachments": null,
            "tipAmount": 0
        },
        "message": "Proceed to find a driver."
    },
    "error": null
}